stix2/__init__.py
stix2/base.py
stix2/custom.py
stix2/environment.py
stix2/exceptions.py
stix2/hashes.py
stix2/parsing.py
stix2/pattern_visitor.py
stix2/patterns.py
stix2/properties.py
stix2/registration.py
stix2/registry.py
stix2/serialization.py
stix2/utils.py
stix2/version.py
stix2/versioning.py
stix2/workbench.py
stix2/canonicalization/Canonicalize.py
stix2/canonicalization/NumberToJson.py
stix2/canonicalization/__init__.py
stix2/confidence/__init__.py
stix2/confidence/scales.py
stix2/datastore/__init__.py
stix2/datastore/filesystem.py
stix2/datastore/filters.py
stix2/datastore/memory.py
stix2/datastore/taxii.py
stix2/equivalence/__init__.py
stix2/equivalence/graph/__init__.py
stix2/equivalence/object/__init__.py
stix2/equivalence/pattern/__init__.py
stix2/equivalence/pattern/compare/__init__.py
stix2/equivalence/pattern/compare/comparison.py
stix2/equivalence/pattern/compare/observation.py
stix2/equivalence/pattern/transform/__init__.py
stix2/equivalence/pattern/transform/comparison.py
stix2/equivalence/pattern/transform/observation.py
stix2/equivalence/pattern/transform/specials.py
stix2/markings/__init__.py
stix2/markings/granular_markings.py
stix2/markings/object_markings.py
stix2/markings/utils.py
stix2/v20/__init__.py
stix2/v20/base.py
stix2/v20/bundle.py
stix2/v20/common.py
stix2/v20/observables.py
stix2/v20/sdo.py
stix2/v20/sro.py
stix2/v20/vocab.py
stix2/v21/__init__.py
stix2/v21/base.py
stix2/v21/bundle.py
stix2/v21/common.py
stix2/v21/observables.py
stix2/v21/sdo.py
stix2/v21/sro.py
stix2/v21/vocab.py
stix2-3.0.0.dist-info/LICENSE
stix2-3.0.0.dist-info/METADATA
stix2-3.0.0.dist-info/WHEEL
stix2-3.0.0.dist-info/top_level.txt
stix2-3.0.0.dist-info/RECORD
