Metadata-Version: 2.1
Name: stix2
Version: 3.0.0
Summary: Produce and consume STIX 2 JSON content
Home-page: https://oasis-open.github.io/cti-documentation/
Author: OASIS Cyber Threat Intelligence Technical Committee
Author-email: cti-users@lists.oasis-open.org
Maintainer: Chris Lenk, Emmanuelle Vargas-Gonzalez
Maintainer-email: clenk@mitre.org, emmanuelle@mitre.org
License: BSD
Project-URL: Documentation, https://stix2.readthedocs.io/
Project-URL: Source Code, https://github.com/oasis-open/cti-python-stix2/
Project-URL: Bug Tracker, https://github.com/oasis-open/cti-python-stix2/issues/
Keywords: stix stix2 json cti cyber threat intelligence
Platform: UNKNOWN
Classifier: Development Status :: 4 - Beta
Classifier: Intended Audience :: Developers
Classifier: Topic :: Security
Classifier: License :: OSI Approved :: BSD License
Classifier: Programming Language :: Python :: 3
Classifier: Programming Language :: Python :: 3.6
Classifier: Programming Language :: Python :: 3.7
Classifier: Programming Language :: Python :: 3.8
Classifier: Programming Language :: Python :: 3.9
Requires-Python: >=3.6
Requires-Dist: pytz
Requires-Dist: requests
Requires-Dist: simplejson
Requires-Dist: stix2-patterns (>=1.2.0)
Provides-Extra: semantic
Requires-Dist: haversine ; extra == 'semantic'
Requires-Dist: rapidfuzz ; extra == 'semantic'
Provides-Extra: taxii
Requires-Dist: taxii2-client (>=2.3.0) ; extra == 'taxii'
